LICENSE
MANIFEST.in
README.md
setup.py
src/javascript_fixes/__init__.py
src/javascript_fixes/__main__.py
src/javascript_fixes/config.py
src/javascript_fixes/connection.py
src/javascript_fixes/errors.py
src/javascript_fixes/events.py
src/javascript_fixes/json_patch.py
src/javascript_fixes/packageinstall.py
src/javascript_fixes/proxy.py
src/javascript_fixes/pyi.py
src/javascript_fixes.egg-info/PKG-INFO
src/javascript_fixes.egg-info/SOURCES.txt
src/javascript_fixes.egg-info/dependency_links.txt
src/javascript_fixes.egg-info/requires.txt
src/javascript_fixes.egg-info/top_level.txt
src/javascript_fixes/js/bridge.js
src/javascript_fixes/js/deps.js
src/javascript_fixes/js/errors.js
src/javascript_fixes/js/pyi.js